iranintl/__init__.py
iranintl/_utils.py
iranintl/iranintl.py
iranintl/types.py
iranintl-0.1.1.dist-info/licenses/LICENSE
iranintl-0.1.1.dist-info/METADATA
iranintl-0.1.1.dist-info/WHEEL
iranintl-0.1.1.dist-info/top_level.txt
iranintl-0.1.1.dist-info/RECORD
