Metadata-Version: 2.4
Name: iranintl
Version: 0.1.1
Summary: A Python library to scrape data from Iran International news
Home-page: https://github.com/navidpgg/iranintl
Author: Navid Poladi
Author-email: navidpoladi99@example.com
Classifier: Programming Language :: Python :: 3
Classifier: License :: OSI Approved :: MIT License
Classifier: Operating System :: OS Independent
Requires-Python: >=3.6
License-File: LICENSE
Requires-Dist: requests
Requires-Dist: beautifulsoup4
Requires-Dist: persiantools
Dynamic: author
Dynamic: author-email
Dynamic: classifier
Dynamic: description
Dynamic: description-content-type
Dynamic: home-page
Dynamic: license-file
Dynamic: requires-dist
Dynamic: requires-python
Dynamic: summary
